README.md
setup.cfg
setup.py
firestore_odm/__init__.py
firestore_odm/collection_mixin.py
firestore_odm/config.py
firestore_odm/context.py
firestore_odm/errors.py
firestore_odm/factory.py
firestore_odm/fields.py
firestore_odm/firestore_object.py
firestore_odm/helpers.py
firestore_odm/model_registry.py
firestore_odm/primary_object.py
firestore_odm/query_mixin.py
firestore_odm/referenced_object.py
firestore_odm/schema.py
firestore_odm/serializable.py
firestore_odm/utils.py
firestore_odm.egg-info/PKG-INFO
firestore_odm.egg-info/SOURCES.txt
firestore_odm.egg-info/dependency_links.txt
firestore_odm.egg-info/not-zip-safe
firestore_odm.egg-info/requires.txt
firestore_odm.egg-info/top_level.txt
tests/__init__.py
tests/city_fixtures.py
tests/fixtures.py
tests/test_collection_mixin.py
tests/test_context.py
tests/test_factory.py
tests/test_field.py
tests/test_firestore_object.py
tests/test_integer.py
tests/test_model_registry.py
tests/test_query.py
tests/test_schema.py
tests/test_serializable.py
tests/utils.py